HyperledgerFabricYuanmaShenduJiexi/README.md
HyperledgerFabricYuanmaShenduJiexi/__init__.py
HyperledgerFabricYuanmaShenduJiexi/__main__.py
HyperledgerFabricYuanmaShenduJiexi/file.epub
HyperledgerFabricYuanmaShenduJiexi/index.html
HyperledgerFabricYuanmaShenduJiexi/css/__init__.py
HyperledgerFabricYuanmaShenduJiexi/css/annotations.css
HyperledgerFabricYuanmaShenduJiexi/css/main.css
HyperledgerFabricYuanmaShenduJiexi/css/normalize.css
HyperledgerFabricYuanmaShenduJiexi/css/popup.css
HyperledgerFabricYuanmaShenduJiexi/font/__init__.py
HyperledgerFabricYuanmaShenduJiexi/font/fontello.eot
HyperledgerFabricYuanmaShenduJiexi/font/fontello.svg
HyperledgerFabricYuanmaShenduJiexi/font/fontello.ttf
HyperledgerFabricYuanmaShenduJiexi/font/fontello.woff
HyperledgerFabricYuanmaShenduJiexi/img/__init__.py
HyperledgerFabricYuanmaShenduJiexi/img/annotator-glyph-sprite.png
HyperledgerFabricYuanmaShenduJiexi/img/annotator-icon-sprite.png
HyperledgerFabricYuanmaShenduJiexi/img/apple-touch-icon.png
HyperledgerFabricYuanmaShenduJiexi/img/cancelfullscreen.png
HyperledgerFabricYuanmaShenduJiexi/img/close.png
HyperledgerFabricYuanmaShenduJiexi/img/fullscreen.png
HyperledgerFabricYuanmaShenduJiexi/img/loader.gif
HyperledgerFabricYuanmaShenduJiexi/img/menu-icon.png
HyperledgerFabricYuanmaShenduJiexi/img/save.png
HyperledgerFabricYuanmaShenduJiexi/img/saved.png
HyperledgerFabricYuanmaShenduJiexi/img/settings-s.png
HyperledgerFabricYuanmaShenduJiexi/img/settings.png
HyperledgerFabricYuanmaShenduJiexi/img/star.png
HyperledgerFabricYuanmaShenduJiexi/js/__init__.py
HyperledgerFabricYuanmaShenduJiexi/js/epub.js
HyperledgerFabricYuanmaShenduJiexi/js/epub.min.js
HyperledgerFabricYuanmaShenduJiexi/js/epub.min.map
HyperledgerFabricYuanmaShenduJiexi/js/hooks.min.js
HyperledgerFabricYuanmaShenduJiexi/js/hooks.min.map
HyperledgerFabricYuanmaShenduJiexi/js/reader.js
HyperledgerFabricYuanmaShenduJiexi/js/reader.js.map
HyperledgerFabricYuanmaShenduJiexi/js/reader.min.js
hyperledger_fabric_yuanma_shendu_jiexi-2024.3.4.0.dist-info/METADATA
hyperledger_fabric_yuanma_shendu_jiexi-2024.3.4.0.dist-info/WHEEL
hyperledger_fabric_yuanma_shendu_jiexi-2024.3.4.0.dist-info/entry_points.txt
hyperledger_fabric_yuanma_shendu_jiexi-2024.3.4.0.dist-info/top_level.txt
hyperledger_fabric_yuanma_shendu_jiexi-2024.3.4.0.dist-info/RECORD
